{
    "per_channel": true,
    "reduce_range": true,
    "per_model_config": {
        "model": {
            "op_types": [
                "ReduceMean",
                "Gather",
                "Shape",
                "Erf",
                "Div",
                "Slice",
                "MatMul",
                "Pow",
                "Constant",
                "Cast",
                "Transpose",
                "Concat",
                "Mul",
                "Sub",
                "Unsqueeze",
                "Softmax",
                "Add",
                "Sqrt",
                "Reshape"
            ],
            "weight_type": "QInt8"
        }
    }
}